image_processor/__init__.py
image_processor/__main__.py
image_processor/core.py
image_processor/image_utils.py
image_processor/processing.py
image_processor_alexsva-0.1.0.dist-info/METADATA
image_processor_alexsva-0.1.0.dist-info/WHEEL
image_processor_alexsva-0.1.0.dist-info/top_level.txt
image_processor_alexsva-0.1.0.dist-info/RECORD
