Metadata-Version: 2.1
Name: image_processor_alexsva
Version: 0.1.0
Summary: Python package to perform various image processing tasks
Author: Alex Silva
Author-email: alex.paulo100@gmail.com
Requires-Python: >=3.12
Requires-Dist: contourpy
Requires-Dist: cycler
Requires-Dist: fonttools
Requires-Dist: imageio
Requires-Dist: kiwisolver
Requires-Dist: lazy-loader
Requires-Dist: matplotlib
Requires-Dist: networkx
Requires-Dist: numpy
Requires-Dist: packaging
Requires-Dist: pillow
Requires-Dist: pyparsing
Requires-Dist: python-dateutil
Requires-Dist: ruff
Requires-Dist: scikit-image
Requires-Dist: scipy
Requires-Dist: setuptools
Requires-Dist: six
Requires-Dist: tifffile
Requires-Dist: twine
Requires-Dist: wheel
Requires-Dist: zipp
